{
  "HELP_DESC": "Створює текст із ударним шрифтом на випадкове зображення",
  "USAGE_EXAMPLE_1": "Створити ударне зображення із випадкового зображення та повідомлень цього каналу",
  "USAGE_EXAMPLE_2": "Створити ударне зображення із випадкового зображення та повідомлень каналу` # general` ",
  "USAGE_EXAMPLE_3": "Створити ударне зображення з аватара ** andre ** та повідомлень каналу `#memez` ",
  "USAGE_EXAMPLE_4": "Створити ударне зображення із передбаченого посилання на зображення та повідомлень цього каналу"
}