{
"HELP_DESC": "Видалити історію повідомлень каналу в базі даних",
"PROMPT": "Ви впевнені, що хочете стерти всі збережені повідомлення?",
    "PROMPT_PATTERN": "Ви впевнені, що хочете стерти всі збережені повідомлення, що містять ваш текст?",
    "PROMPT_FOOTER": "Введіть`% confirm% `, щоб стерти їх, або`% cancel% `, щоб скасувати цю дію.",
    "WIPED": "усі збережені повідомлення успішно стерто.",
    "WIPED_PATTERN": "усі збережені повідомлення, що включають наданий текст, успішно стерто."
}